duty_board/__init__.py
duty_board/__main__.py
duty_board/alembic.ini
duty_board/exceptions.py
duty_board/server.py
duty_board/worker_loop.py
duty_board/alchemy/__init__.py
duty_board/alchemy/add_sqladmin.py
duty_board/alchemy/api_queries.py
duty_board/alchemy/session.py
duty_board/alchemy/settings.py
duty_board/alchemy/sqlalchemy_types.py
duty_board/alchemy/update_duty_calendars.py
duty_board/alembic/__init__.py
duty_board/alembic/env.py
duty_board/alembic/versions/2023_11_28_1113-9af1232f6bc0_initial_version.py
duty_board/alembic/versions/__init__.py
duty_board/models/__init__.py
duty_board/models/calendar.py
duty_board/models/on_call_event.py
duty_board/models/person.py
duty_board/models/person_image.py
duty_board/models/token.py
duty_board/plugin/__init__.py
duty_board/plugin/abstract_plugin.py
duty_board/plugin/ical_plugin_mixin.py
duty_board/plugin/ldap_plugin_mixin.py
duty_board/plugin/example/__init__.py
duty_board/plugin/example/example_logo.png
duty_board/plugin/example/example_plugin.py
duty_board/plugin/example/favicon.ico
duty_board/plugin/helpers/__init__.py
duty_board/plugin/helpers/duty_calendar_config.py
duty_board/plugin/helpers/ldap_helper.py
duty_board/plugin/helpers/plugin_fetcher.py
duty_board/web_helpers/__init__.py
duty_board/web_helpers/generate_typescript_api.py
duty_board/web_helpers/gzip_static_files.py
duty_board/web_helpers/response_types.py
duty_board/www/dist/index.html
duty_board/www/dist/assets/index-4Js4B9Lo.js
duty_board/www/dist/assets/index-4Js4B9Lo.js.gz
duty_board/www/dist/assets/index-UzPCcAUx.js
duty_board/www/dist/assets/index-UzPCcAUx.js.gz
duty_board/www/dist/assets/style-vPjAiatq.css
duty_board/www/dist/assets/style-vPjAiatq.css.gz
duty_board/www/static/favicon.ico
duty_board/www/static/logo192.png
duty_board/www/static/logo512.png
duty_board/www/static/manifest.json
duty_board/www/static/robots.txt
duty_board/www/user_images/bert.jpeg
duty_board/www/user_images/bert2.jpg
duty_board-0.3.1.dist-info/LICENSE
duty_board-0.3.1.dist-info/METADATA
duty_board-0.3.1.dist-info/WHEEL
duty_board-0.3.1.dist-info/entry_points.txt
duty_board-0.3.1.dist-info/top_level.txt
duty_board-0.3.1.dist-info/RECORD
