Metadata-Version: 2.1
Name: duty-board
Version: 0.3.1
Summary: Package to display an overview of all active Duty rosters you have at your Company using iCalendars.
Author-email: Jorrick Sleijster <jorricks3@gmail.com>
License: Apache License
Project-URL: Home, https://github.com/Jorricks/DutyBoard
Project-URL: Documentation, https://github.com/Jorricks/DutyBoard
Project-URL: Source, https://github.com/Jorricks/DutyBoard
Project-URL: PullRequests, https://github.com/Jorricks/DutyBoard/pulls
Project-URL: Issues, https://github.com/Jorricks/DutyBoard/issues
Classifier: Intended Audience :: Information Technology
Classifier: Intended Audience :: Developers
Classifier: Operating System :: OS Independent
Classifier: Topic :: Communications
Classifier: Topic :: Communications :: Conferencing
Classifier: Topic :: Office/Business
Classifier: Topic :: Office/Business :: Office Suites
Classifier: Topic :: Internet
Classifier: Topic :: Software Development
Classifier: Topic :: Software Development :: Libraries
Classifier: Topic :: Software Development :: Libraries :: Python Modules
Classifier: Topic :: Software Development :: Libraries :: Application Frameworks
Classifier: Typing :: Typed
Classifier: License :: OSI Approved :: MIT License
Classifier: Development Status :: 4 - Beta
Classifier: Programming Language :: Python
Classifier: Programming Language :: Python :: 3
Classifier: Programming Language :: Python :: 3 :: Only
Classifier: Programming Language :: Python :: 3.8
Classifier: Programming Language :: Python :: 3.9
Classifier: Programming Language :: Python :: 3.10
Classifier: Programming Language :: Python :: 3.11
Requires-Python: >=3.8
License-File: LICENSE
Requires-Dist: alembic <2.0.0,>=1.12.1
Requires-Dist: fastapi >=0.87.0
Requires-Dist: ical-library >=0.1.0
Requires-Dist: itsdangerous >=2.1.2
Requires-Dist: pendulum <3.0.0,>=2.0.0
Requires-Dist: psycopg2-binary >=2.9.0
Requires-Dist: pydantic <3.0.0,>=2.4.0
Requires-Dist: pytz >=2022.6
Requires-Dist: requests >=2.28.1
Requires-Dist: sqladmin >=0.8.0
Requires-Dist: sqlalchemy <3.0.0,>=2.0.23
Requires-Dist: tzlocal >=4.2
Requires-Dist: uvicorn >=0.20.0
Provides-Extra: dev
Requires-Dist: docker <7.0.0,>=6.1.3 ; extra == 'dev'
Requires-Dist: httpx <1.0.0,>=0.25.2 ; extra == 'dev'
Requires-Dist: ruff <1.0.0,>=0.1.4 ; extra == 'dev'
Requires-Dist: mypy <2.0.0,>=1.6.1 ; extra == 'dev'
Requires-Dist: pre-commit <3.0.0,>=2.19.0 ; extra == 'dev'
Requires-Dist: pytest <8.0.0,>=7.4.3 ; extra == 'dev'
Requires-Dist: pytest-cov <5.0.0,>=4.0.0 ; extra == 'dev'
Requires-Dist: pytest-asyncio <1.0.0,>=0.21.1 ; extra == 'dev'
Requires-Dist: requests-mock <2.0.0,>=1.11.0 ; extra == 'dev'
Requires-Dist: sqlalchemy[mypy] <3.0.0,>=2.0.23 ; extra == 'dev'
Requires-Dist: types-pytz >=2022.6.0.1 ; extra == 'dev'
Requires-Dist: types-tzlocal >=4.2.2.0 ; extra == 'dev'
Provides-Extra: doc
Requires-Dist: mkdocs <2.0.0,>=1.3.0 ; extra == 'doc'
Requires-Dist: mkdocs-material <9.0.0,>=8.3.9 ; extra == 'doc'
Requires-Dist: mkdocstrings[python] <1.0.0,>=0.19.0 ; extra == 'doc'
Requires-Dist: termynal <1.0.0,>=0.2.0 ; extra == 'doc'
Provides-Extra: ldap
Requires-Dist: ldap3 <3.0.0,>=2.9.1 ; extra == 'ldap'
Requires-Dist: Pillow <11.0.0,>=10.1.0 ; extra == 'ldap'
